dashai_test_tabular_classification_package/__init__.py
dashai_test_tabular_classification_package/k_neighbors_classifier.py
dashai_test_tabular_classification_package/logistic_regression.py
dashai_test_tabular_classification_package/random_forest_classifier.py
dashai_test_tabular_classification_package/svc.py
dashai_test_tabular_classification_package/tabular_classification_model.py
dashai_test_tabular_classification_package/tabular_classification_task.py
dashai_test_tabular_classification_package-0.1.3.dist-info/METADATA
dashai_test_tabular_classification_package-0.1.3.dist-info/WHEEL
dashai_test_tabular_classification_package-0.1.3.dist-info/entry_points.txt
dashai_test_tabular_classification_package-0.1.3.dist-info/RECORD
