Metadata-Version: 2.3
Name: dashai_test_tabular_classification_package
Version: 0.1.3
Summary: Tabular Classification Package
Project-URL: Homepage, https://github.com/DashAISoftware/DashAI
Project-URL: Issues, https://github.com/DashAISoftware/DashAI/issues
Author: DashAI team
Author-email: dashaisoftware@gmail.com
Keywords: DashAI,Dataloader,Model,Package,Task
Requires-Python: >=3.8
Requires-Dist: scikit-learn>=1.2.1
